{
	"configurations" : 
	[
		{
			"directories" : 
			[
				{
					"build" : ".",
					"jsonFile" : "directory-.-Debug-d0094a50bb2071803777.json",
					"minimumCMakeVersion" : 
					{
						"string" : "3.22"
					},
					"projectIndex" : 0,
					"source" : ".",
					"targetIndexes" : 
					[
						0
					]
				}
			],
			"name" : "Debug",
			"projects" : 
			[
				{
					"directoryIndexes" : 
					[
						0
					],
					"name" : "sixth",
					"targetIndexes" : 
					[
						0
					]
				}
			],
			"targets" : 
			[
				{
					"directoryIndex" : 0,
					"id" : "sixth::@6890427a1f51a3e7e1df",
					"jsonFile" : "target-sixth-Debug-3ad3f5fa924d3ca256b7.json",
					"name" : "sixth",
					"projectIndex" : 0
				}
			]
		}
	],
	"kind" : "codemodel",
	"paths" : 
	{
		"build" : "D:/wodedaima/vscode/dataStructure/sixth/cmake-build-debug",
		"source" : "D:/wodedaima/vscode/dataStructure/sixth"
	},
	"version" : 
	{
		"major" : 2,
		"minor" : 3
	}
}
